efaar_benchmarking/__init__.py
efaar_benchmarking/benchmarking.py
efaar_benchmarking/constants.py
efaar_benchmarking/core.py
efaar_benchmarking/data_loading.py
efaar_benchmarking/efaar.py
efaar_benchmarking/plotting.py
efaar_benchmarking/benchmark_annotations/CORUM.txt
efaar_benchmarking/benchmark_annotations/CORUM_clusters.tsv
efaar_benchmarking/benchmark_annotations/HuMAP.txt
efaar_benchmarking/benchmark_annotations/LICENSE
efaar_benchmarking/benchmark_annotations/Reactome.txt
efaar_benchmarking/benchmark_annotations/SIGNOR.txt
efaar_benchmarking/benchmark_annotations/StringDB.txt
efaar_benchmarking/benchmark_annotations/c5.go.v2023.2.Hs.symbols.gmt
efaar_benchmarking/expression_data/HeLa_expression.csv
efaar_benchmarking/expression_data/U2OS_expression.csv
notebooks/map_building_benchmarking.ipynb
notebooks/map_evaluation_comparison.ipynb
notebooks/data/GWPS_map_cache.pkl
notebooks/data/LICENSE
notebooks/data/cpg0016_map_cache.pkl
notebooks/data/cpg0016_metadata.pkl
notebooks/data/cpg0021_map_cache.pkl
notebooks/data/cpg0021_metadata.pkl
requirements/dev_3.11.txt
requirements/main_3.11.txt
tests/__init__.py
tests/test_benchmarking.py
tests/test_efaar.py
efaar_benchmarking-1.0.dist-info/LICENSE
efaar_benchmarking-1.0.dist-info/METADATA
efaar_benchmarking-1.0.dist-info/WHEEL
efaar_benchmarking-1.0.dist-info/top_level.txt
efaar_benchmarking-1.0.dist-info/RECORD
