Metadata-Version: 2.1
Name: efaar_benchmarking
Version: 1.0
Author-email: Recursion Pharmaceuticals <devs@recursionpharma.com>
Keywords: efaar_benchmarking
Classifier: Operating System :: OS Independent
Classifier: Programming Language :: Python
Classifier: Programming Language :: Python :: 3
Requires-Python: >=3.11
License-File: LICENSE
Requires-Dist: scikit-learn
Requires-Dist: pandas
Requires-Dist: numpy
Requires-Dist: matplotlib
Requires-Dist: matplotlib-venn
Requires-Dist: upsetplotly
Requires-Dist: seaborn
Requires-Dist: scvi-tools
Requires-Dist: wget
Requires-Dist: geomloss
Requires-Dist: torch
Requires-Dist: joblib
Requires-Dist: scipy
Requires-Dist: s3fs
Provides-Extra: dev
Requires-Dist: bandit[toml]; extra == "dev"
Requires-Dist: black; extra == "dev"
Requires-Dist: coverage; extra == "dev"
Requires-Dist: docstr-coverage; extra == "dev"
Requires-Dist: flake8; extra == "dev"
Requires-Dist: isort; extra == "dev"
Requires-Dist: mypy; extra == "dev"
Requires-Dist: pre-commit; extra == "dev"
Requires-Dist: pytest; extra == "dev"
Requires-Dist: pytest-cov; extra == "dev"
Requires-Dist: pyupgrade; extra == "dev"
Requires-Dist: radon; extra == "dev"
Requires-Dist: types-pkg-resources; extra == "dev"
Requires-Dist: types-setuptools; extra == "dev"
Requires-Dist: tox; extra == "dev"
Requires-Dist: validate-pyproject[all]; extra == "dev"
Requires-Dist: jupyterlab; extra == "dev"
